Metadata-Version: 1.1
Name: qmeshcontainers
Version: 1.0.0
Summary: Create Docker container for using and developing qmesh
Home-page: https://www.qmesh.org
Author: The qmesh development team.
Author-email: develop@qmesh.org
License: GPLv3
Download-URL: https://bitbucket.org/qmesh-developers/qmesh-containers/commits/tag/v1.0.0
Keywords: GIS,mesh generation,Docker
Platform: UNKNOWN
